Metadata-Version: 1.2
Name: esprisendmail
Version: 1.2
Summary: CLI to send mail alerts to ESPRI users
Home-page: https://gitlab.in2p3.fr/ipsl/espri/espri-mod/sysadmin/mail_sender
Author: Levavasseur Guillaume
Author-email: glipsl@ipsl.fr
License: UNKNOWN
Platform: Unix
Classifier: Development Status :: 5 - Production/Stable
Classifier: Environment :: Console
Classifier: Intended Audience :: Science/Research
Classifier: Intended Audience :: System Administrators
Classifier: Natural Language :: English
Classifier: Operating System :: Unix
Classifier: Programming Language :: Python
Classifier: Topic :: Scientific/Engineering
Classifier: Topic :: Software Development :: Build Tools
Requires-Python: >3.6
